outlierRemoval_python/outlierRemoval.py
outlier_asharma_3027-1.1.dist-info/METADATA
outlier_asharma_3027-1.1.dist-info/WHEEL
outlier_asharma_3027-1.1.dist-info/entry_points.txt
outlier_asharma_3027-1.1.dist-info/top_level.txt
outlier_asharma_3027-1.1.dist-info/RECORD
