Metadata-Version: 2.1
Name: outlier-asharma-3027
Version: 1.1
Summary: A python package for removing outliers from a dataset using InterQuartile Range (IQR)
Home-page: UNKNOWN
Author: Abhishek Sharma
Author-email: asharma1_be17@thapar.edu
License: UNKNOWN
Platform: UNKNOWN
Classifier: Programming Language :: Python :: 3
Classifier: License :: OSI Approved :: MIT License
Classifier: Operating System :: OS Independent
Requires-Python: >=3.6
Requires-Dist: requests
